MANIFEST.in
README.txt
setup.py
src/.DS_Store
src/medialog/.DS_Store
src/medialog/__init__.py
src/medialog.redirect.egg-info/PKG-INFO
src/medialog.redirect.egg-info/SOURCES.txt
src/medialog.redirect.egg-info/dependency_links.txt
src/medialog.redirect.egg-info/entry_points.txt
src/medialog.redirect.egg-info/namespace_packages.txt
src/medialog.redirect.egg-info/not-zip-safe
src/medialog.redirect.egg-info/requires.txt
src/medialog.redirect.egg-info/top_level.txt
src/medialog/redirect/.DS_Store
src/medialog/redirect/README.txt
src/medialog/redirect/__init__.py
src/medialog/redirect/configure.zcml
src/medialog/redirect/interfaces.py
src/medialog/redirect/browser/.DS_Store
src/medialog/redirect/browser/__init__.py
src/medialog/redirect/browser/configure.zcml
src/medialog/redirect/browser/interfaces.py
src/medialog/redirect/browser/view.py
src/medialog/redirect/profiles/.DS_Store
src/medialog/redirect/profiles/default/.DS_Store
src/medialog/redirect/profiles/default/browserlayer.xml
src/medialog/redirect/profiles/default/metadata.xml
src/medialog/redirect/tests/__init__.py
src/medialog/redirect/tests/base.py
src/medialog/redirect/tests/test_doctest.py
src/medialog/redirect/tests/test_example.py