Metadata-Version: 1.1
Name: medialog.redirect
Version: 0.2.1
Summary: A redirecting browser view
Home-page: http://github.com/espenmn/medialog.redirect
Author: Espen Moe-Nilssen
Author-email: espen at medialog no
License: gpl
Keywords: redirect plone diazo
Platform: UNKNOWN
Classifier: Environment :: Web Environment
Classifier: Framework :: Plone
Classifier: Framework :: Plone :: 4.1
Classifier: Framework :: Plone :: 4.2
Classifier: Framework :: Plone :: 4.3
Classifier: Intended Audience :: Developers
Classifier: Intended Audience :: End Users/Desktop
Classifier: Operating System :: OS Independent
Classifier: Programming Language :: Python
